MANIFEST.in
README.rst
setup.cfg
setup.py
bin/cropfaces
bin/cropfaces.cmd
bin/cropfoldersquares
bin/cropfoldersquares.cmd
bin/cropvideoframes
bin/cropvideoframes.cmd
cropfaces/2haarcascade_frontalface_alt.xml
cropfaces/2haarcascade_frontalface_alt2.xml
cropfaces/2haarcascade_frontalface_alt_tree.xml
cropfaces/2haarcascade_frontalface_default.xml
cropfaces/HS.xml
cropfaces/__init__.py
cropfaces/cropfaces.py
cropfaces/haarcascade_eye.xml
cropfaces/haarcascade_frontalface_alt.xml
cropfaces/haarcascade_frontalface_alt2.xml
cropfaces/haarcascade_frontalface_alt_tree.xml
cropfaces/haarcascade_frontalface_default.xml
cropfaces/haarcascade_profileface.xml
cropfaces/haarcascade_upperbody.xml
cropfaces/parojosG.xml
cropfaces/tool.py
cropfaces/toolFolderSquares.py
cropfaces/toolVideoFrames.py
cropfaces.egg-info/PKG-INFO
cropfaces.egg-info/SOURCES.txt
cropfaces.egg-info/dependency_links.txt
cropfaces.egg-info/not-zip-safe
cropfaces.egg-info/requires.txt
cropfaces.egg-info/top_level.txt