Metadata-Version: 1.1
Name: cropfaces
Version: 0.0.77
Summary: Librería Python: Recorta imágenes dejando las caras para adaptarse a una escala concreta.
Home-page: https://github.com/tuaplicacionpropia/cropfaces
Author: tuaplicacionpropia.com
Author-email: tuaplicacionpropia@gmail.com
License: MIT
Download-URL: https://github.com/tuaplicacionpropia/cropfaces/archive/master.zip
Keywords: jpg,png
Platform: any
Classifier: Development Status :: 4 - Beta
Classifier: License :: OSI Approved :: MIT License
Classifier: Programming Language :: Python
Classifier: Programming Language :: Python :: 2.7
Classifier: Intended Audience :: Developers
Classifier: Topic :: Multimedia :: Graphics
